py4envi/__init__.py
py4envi/__main__.py
py4envi/cli.py
py4envi/frames.py
py4envi/products.py
py4envi/scenes.py
py4envi/search.py
py4envi/token.py
py4envi/util.py
py4envi_openapi_client/__init__.py
py4envi_openapi_client/api_client.py
py4envi_openapi_client/configuration.py
py4envi_openapi_client/exceptions.py
py4envi_openapi_client/model_utils.py
py4envi_openapi_client/rest.py
py4envi_openapi_client/api/__init__.py
py4envi_openapi_client/api/auth_api.py
py4envi_openapi_client/api/product_api.py
py4envi_openapi_client/api/scene_api.py
py4envi_openapi_client/api/search_api.py
py4envi_openapi_client/apis/__init__.py
py4envi_openapi_client/model/__init__.py
py4envi_openapi_client/model/basic_product_category_response.py
py4envi_openapi_client/model/basic_product_response.py
py4envi_openapi_client/model/login_request.py
py4envi_openapi_client/model/search_response.py
py4envi_openapi_client/model/token_response.py
py4envi_openapi_client/models/__init__.py
py4envi-0.0.3.dist-info/LICENSE
py4envi-0.0.3.dist-info/METADATA
py4envi-0.0.3.dist-info/WHEEL
py4envi-0.0.3.dist-info/entry_points.txt
py4envi-0.0.3.dist-info/top_level.txt
py4envi-0.0.3.dist-info/RECORD
