Metadata-Version: 2.1
Name: py4envi
Version: 0.0.3
Summary: Library/cli tool for https://dane.sat4envi.imgw.pl/
Home-page: https://github.com/konradmalik/py4envi
Author: Konrad Malik
Author-email: konrad.malik@gmail.com
License: LGPL-2.1
Platform: UNKNOWN
Classifier: License :: OSI Approved :: GNU Lesser General Public License v2 or later (LGPLv2+)
Classifier: Programming Language :: Python :: 3
Classifier: Programming Language :: Python :: 3.7
Classifier: Programming Language :: Python :: 3.8
Classifier: Programming Language :: Python :: 3.9
Requires-Python: >=3.7
License-File: LICENSE
Requires-Dist: urllib3 (>=1.25.3)
Requires-Dist: requests (>=2.25.1)
Requires-Dist: python-dateutil (>=2.8.1)
Requires-Dist: Shapely (>=1.7.1)
Requires-Dist: geopandas (>=0.9.0)
Requires-Dist: tqdm (>=4.60.0)
